{
  "faq_header": "ხშირად დასმული კითხვები",
  "faqs": [
    {
      "faq_question": "რამდენია მიწოდების საფასური?",
      "faq_answer": "* თბილისში მიწოდება - 5₾\n* სხვა დიდ ქალაქებში - 5₾\n* სოფლებსა და დაბებში - 13₾"
    },
    {
      "faq_question": "რა ღირს სასაჩუქრე შეფუთვა?",
      "faq_answer": "სასაჩუქრე შეფუთვის საფასური შედის პროდუქციის ღირებულებაში."
    },
    {
      "faq_question": "როგორ გავხდე Garter Club-ის წევრი?",
      "faq_answer": "მოგვწერეთ პირად შეტყობინებაში შემდეგი ინფორმაცია:\n\n* სახელი და გვარი\n* მისამართი\n* დაბადების თარიღი\n\n და ჩვენ დაგიმზადებთ პერსონალურ ვირტუალურ VIP ბარათს!"
    },
    {
      "faq_question": "რა ღირს Garter Club-ის წევრობა?",
      "faq_answer": "წევრობა უფასოა"
    },
    {
      "faq_question": "რა უპირატესობებით ვისარგებლებ Garter Club-ში გაწევრიანების შემდეგ?",
      "faq_answer": "* **პირველები გაეცნობით ჩვენს ახალ კოლექციებს!**\n* ისარგებლეთ **10%-იანი მუდმივი ფასდაკლებით**!\n* **უფასო მიწოდება** ყველა შეკვეთაზე!\n*  დაბადების დღეზე გელით **დამატებითი სპეციალური ფასდაკლებები**!"
    }
  ]
}
